aiouring.libs/liburing-39bf6bbd.so.2.2
aiouring-0.1.0.dist-info/RECORD
aiouring-0.1.0.dist-info/top_level.txt
aiouring-0.1.0.dist-info/WHEEL
aiouring-0.1.0.dist-info/METADATA
aiouring-0.1.0.dist-info/LICENSE
aiouring-0.1.0.data/headers/UringWraper.hpp
aiouring/_core.cpython-310-x86_64-linux-gnu.so
aiouring/__init__.py
aiouring/_core/UringProactor.pyx
