Metadata-Version: 2.1
Name: aiouring
Version: 0.1.0
Summary: An io_uring adapter for asyncio, depends on liburing.so
Home-page: https://github.com/GhostSignal/aiouring
Author: GhostSignal
Author-email: 2685780449@qq.com
License: MIT
Platform: linux
Classifier: License :: OSI Approved :: MIT License
Classifier: Topic :: System :: Networking
Classifier: Programming Language :: Cython
Classifier: Programming Language :: Python :: 3
Requires-Python: >=3.6.0
License-File: LICENSE
